kuzu_wasm/__init__.py
kuzu_wasm/utils.py
kuzu_wheel/__init__.py
kuzu_wheel/utils.py
kuzu_wasm-0.0.9.dist-info/METADATA
kuzu_wasm-0.0.9.dist-info/WHEEL
kuzu_wasm-0.0.9.dist-info/top_level.txt
kuzu_wasm-0.0.9.dist-info/RECORD
