Metadata-Version: 2.1
Name: kuzu_wasm
Version: 0.0.9
Summary: Python wheel for kuzu_wasm
Home-page: https://github.com/DylanShang/kuzu-lab
Author: DylanShang
Author-email: lantu.april@gmail.com
Keywords: jupyterlite kuzu wasm
Requires-Dist: pandas
Requires-Dist: networkx
